watsonx_agent_deploy/__init__.py
watsonx_agent_deploy/cli.py
watsonx_agent_deploy/config.py
watsonx_agent_deploy/deployer.py
watsonx_agent_deploy/deployer_ver1.py
watsonx_agent_deploy-0.1.3.dist-info/licenses/LICENSE
watsonx_agent_deploy-0.1.3.dist-info/METADATA
watsonx_agent_deploy-0.1.3.dist-info/WHEEL
watsonx_agent_deploy-0.1.3.dist-info/entry_points.txt
watsonx_agent_deploy-0.1.3.dist-info/top_level.txt
watsonx_agent_deploy-0.1.3.dist-info/RECORD
