Metadata-Version: 2.4
Name: watsonx-agent-deploy
Version: 0.1.3
Summary: Deploy multiple AI agents to watsonx.ai at once
Author-email: Ishan Singh <ishans2404@gmail.com>
License: MIT
Project-URL: Homepage, https://github.com/ishans2404/watsonx-agent-deploy
Project-URL: Issues, https://github.com/ishans2404/watsonx-agent-deploy/issues
Requires-Python: >=3.8
License-File: LICENSE
Requires-Dist: python-dotenv>=1.0.0
Requires-Dist: ibm-watsonx-ai-cli
Requires-Dist: tomlkit>=0.11.0
Requires-Dist: click>=8.0.0
Dynamic: license-file
